[
  {
    "id": "DC658B4F-A0EB-4C20-B296-E0D57E8DA6DB",
    "name": "GB verification policy",
    "regionType": "Country",
    "region": "GB",
    "tasks": [
      {
        "id": "D06A5360-BD42-490E-82EB-C910BA66ACFF",
        "name": "Identity task",
        "type": "Identity",
        "priority": 1,
        "autoCompletePolicy": "EveryTime",
        "collectionSteps": [
          {
            // "Onboarding survey"
            "xPath": "Survey.C5E7A138-2E36-43D0-BD76-43A606068F49",
            "isReviewNeeded": false,
            "isRequired": true
          }
        ],
        "checksVariants": [
          "D6F2DAF9-3F8F-4335-A7B8-4FC383471A1D", // "Onfido document check"
          "3B43F013-5AC2-4BD9-96DE-20A683331BCF" // "Onfido facial similarity check by photo"
        ]
      },
      {
        "id": "F8743F21-A511-45A3-AB03-E833AB639AFA",
        "name": "Tax residence",
        "type": "TaxResidence",
        "priority": 2,
        "autoCompletePolicy": "EveryTime",
        "checksVariants": [
          "A9E0048B-0F6B-44F0-8A22-703DD86BA05E" // "Tax residence check"
        ]
      },
      {
        "id": "62BA1278-C7F7-42D1-A901-0548FDB1A4DB",
        "name": "User duplication screening",
        "type": "DuplicationScreening",
        "priority": 1,
        "autoCompletePolicy": "EveryTime",
        "checksVariants": [
          "372929F1-8597-4E50-A5CE-5881377AF295", // "Name and date of birth duplication"
          "0822EFCF-5F04-4D10-A144-460E2040968E", // "Onfido known face check by photo"
          "62BA1CC3-8802-4C13-B2BA-BB6EFBDBEE1F" // "Id document number duplication"
        ]
      },
      {
        "id": "543EC1A7-6141-4491-9CA6-3691BBDDB7EE",
        "name": "User address",
        "type": "Address",
        "priority": 2,
        "autoCompletePolicy": "EveryTime",
        "checksVariants": [
          "FE22EBBC-DA71-43A9-883C-B15F0124F0E3", // "Check country by IP match"
          "63EAA27A-A6FC-43A8-93E4-0D7BFBD7CF23" // Onfido identity enhanced check
        ]
      },
      {
        "id": "9A1C60FB-6F96-431B-ABDB-11B5FC9C5CA5",
        "name": "Risk lists screening",
        "type": "RiskListsScreening",
        "priority": 3,
        "autoCompletePolicy": "EveryTime",
        "collectionSteps": [
          {
            "xPath": "VerificationDetails.IsPep",
            "isReviewNeeded": false,
            "isRequired": true
          },
          {
            "xPath": "VerificationDetails.IsAdverseMedia",
            "isReviewNeeded": false,
            "isRequired": true
          },
          {
            "xPath": "VerificationDetails.IsSanctioned",
            "isReviewNeeded": false,
            "isRequired": true
          }
        ],
        "checksVariants": [ "BB30DACB-F8A0-477C-941A-FB0C71C0297A" ]
      }
    ],
    "triggers": [
      {
        "id": "222E9D58-CACB-4094-9399-2AA50AA2D766",
        "name": "Proof of funds/wealth assessment",
        "conditions": [
          {
            "type": "RiskLevel",
            "value": "High"
          }
        ],
        "commands": [
          {
            "type": "AddTask",
            "config": {
              "variantId": "C1B826B7-6E0A-4AB3-813D-4393E0C0E095"
            }
          },
          {
            "type": "AddCollectionStep",
            "config": {
              "taskType": "ProofOfFunds",
              "collectionStep": {
                "xPath": "Documents.ProofOfFunds",
                "isReviewNeeded": true,
                "isRequired": true
              }
            }
          },
          {
            "type": "AddCollectionStep",
            "config": {
              "taskType": "ProofOfFunds",
              "collectionStep": {
                //SoF survey
                "xPath": "Survey.0FB7492B-7DC5-4277-A7FF-F3D07376FF66",
                "isReviewNeeded": false,
                "isRequired": true
              }
            }
          }
        ]
      },
      {
        "id": "AF4321CB-E246-479A-9F13-84AC8942C078",
        "name": "Financial stability assessment",
        "conditions": [
          {
            "type": "RiskLevel",
            "value": "High"
          }
        ],
        "commands": [
          {
            "type": "AddTask",
            "config": {
              "variantId": "CF9F0CA8-6535-4F4A-B2D3-71AB075EC841"
            }
          },
          {
            "type": "AddCollectionStep",
            "config": {
              "taskType": "FinancialCondition",
              "collectionStep": {
                // "Occupation/income survey" 
                "xPath": "Survey.F9A2A3AC-6E98-43C9-BAB2-794E8E6DF686",
                "isReviewNeeded": false,
                "isRequired": true
              }
            }
          }
        ]
      },
      {
        "id": "D064BF48-8B8C-44C7-851C-59A69E78C37A",
        "name": "Require POA documents for HighRisk",
        "conditions": [
          {
            "type": "RiskLevel",
            "value": "High"
          }
        ],
        "commands": [
          {
            "type": "AddCollectionStep",
            "config": {
              "taskType": "Address",
              "collectionStep": {
                "xPath": "Documents.ProofOfAddress",
                "isReviewNeeded": true,
                "isRequired": true
              }
            }
          }
        ]
      }
    ],
    "templates": [
      {
        "id": "C1B826B7-6E0A-4AB3-813D-4393E0C0E095",
        "name": "Proof of funds/wealth assessment",
        "type": "ProofOfFunds",
        "priority": 4,
        "autoCompletePolicy": "EveryTime"
      },
      {
        "id": "CF9F0CA8-6535-4F4A-B2D3-71AB075EC841",
        "name": "Financial stability assessment",
        "type": "FinancialCondition",
        "priority": 4,
        "autoCompletePolicy": "EveryTime"
      }
    ],
    "rejectionPolicy": {
      "conditions": [
        {
          "type": "RiskLevel",
          "value": "ExtraHigh"
        }
      ]
    }
  }
]